watchedserial
