Metadata-Version: 1.0
Name: watchedserial
Version: 1.0.1
Summary: Module for handling pySerial Serial objects connecting and disconnecting
Home-page: UNKNOWN
Author: Eric Oswald
Author-email: eoswald39@gmail.com
License: MIT
Platform: UNKNOWN
